sklearn/calibration.py
sklearn/exceptions.py
sklearn/base.py
sklearn/_distributor_init.py
sklearn/_min_dependencies.py
sklearn/isotonic.py
sklearn/dummy.py
sklearn/random_projection.py
sklearn/__init__.py
sklearn/discriminant_analysis.py
sklearn/multiclass.py
sklearn/multioutput.py
sklearn/_config.py
sklearn/conftest.py
sklearn/kernel_ridge.py
sklearn/_isotonic.cpython-312-x86_64-linux-gnu.so
sklearn/kernel_approximation.py
sklearn/naive_bayes.py
sklearn/pipeline.py
sklearn/impute/_iterative.py
sklearn/impute/_knn.py
sklearn/impute/_base.py
sklearn/impute/__init__.py
sklearn/impute/tests/test_base.py
sklearn/impute/tests/test_impute.py
sklearn/impute/tests/__init__.py
sklearn/impute/tests/test_knn.py
sklearn/impute/tests/test_common.py
sklearn/compose/_target.py
sklearn/compose/__init__.py
sklearn/compose/_column_transformer.py
sklearn/compose/tests/test_target.py
sklearn/compose/tests/__init__.py
sklearn/compose/tests/test_column_transformer.py
sklearn/cluster/_hierarchical_fast.cpython-312-x86_64-linux-gnu.so
sklearn/cluster/_k_means_minibatch.cpython-312-x86_64-linux-gnu.so
sklearn/cluster/_mean_shift.py
sklearn/cluster/_kmeans.py
sklearn/cluster/_hierarchical_fast.pxd
sklearn/cluster/__init__.py
sklearn/cluster/_bisect_k_means.py
sklearn/cluster/_birch.py
sklearn/cluster/_k_means_elkan.cpython-312-x86_64-linux-gnu.so
sklearn/cluster/_feature_agglomeration.py
sklearn/cluster/_bicluster.py
sklearn/cluster/_k_means_common.pxd
sklearn/cluster/_dbscan.py
sklearn/cluster/_optics.py
sklearn/cluster/_affinity_propagation.py
sklearn/cluster/_agglomerative.py
sklearn/cluster/_dbscan_inner.cpython-312-x86_64-linux-gnu.so
sklearn/cluster/_spectral.py
sklearn/cluster/_k_means_common.cpython-312-x86_64-linux-gnu.so
sklearn/cluster/_k_means_lloyd.cpython-312-x86_64-linux-gnu.so
sklearn/cluster/_hdbscan/_linkage.cpython-312-x86_64-linux-gnu.so
sklearn/cluster/_hdbscan/hdbscan.py
sklearn/cluster/_hdbscan/_tree.pxd
scikit_learn-1.4.0.dist-info/WHEEL
scikit_learn-1.4.0.dist-info/RECORD
scikit_learn-1.4.0.dist-info/top_level.txt
scikit_learn-1.4.0.dist-info/COPYING
scikit_learn-1.4.0.dist-info/METADATA
